google_meet_bot/__init__.py
google_meet_bot/__main__.py
google_meet_bot/cli.py
google_meet_bot/join_google_meet.py
google_meet_bot/record_audio.py
google_meet_bot/speech_to_text.py
google_meet_bot-0.0.1.dist-info/METADATA
google_meet_bot-0.0.1.dist-info/WHEEL
google_meet_bot-0.0.1.dist-info/entry_points.txt
google_meet_bot-0.0.1.dist-info/licenses/LICENSE
google_meet_bot-0.0.1.dist-info/RECORD
