Metadata-Version: 2.4
Name: google-meet-bot
Version: 0.0.1
Summary: Automate joining Google Meet, record audio, transcribe with Whisper, and summarize using GPT.
Project-URL: Homepage, https://github.com/dhruvldrp9/Google-Meet-Bot
Project-URL: Repository, https://github.com/dhruvldrp9/Google-Meet-Bot
Project-URL: Issues, https://github.com/dhruvldrp9/Google-Meet-Bot/issues
Author: Dhruv Patel
License: MIT License
License-File: LICENSE
Keywords: audio,bot,google-meet,openai,selenium,transcription,whisper
Classifier: Environment :: Console
Classifier: Intended Audience :: Developers
Classifier: License :: OSI Approved :: MIT License
Classifier: Programming Language :: Python
Classifier: Programming Language :: Python :: 3
Classifier: Programming Language :: Python :: 3 :: Only
Classifier: Programming Language :: Python :: 3.8
Classifier: Programming Language :: Python :: 3.9
Classifier: Programming Language :: Python :: 3.10
Classifier: Programming Language :: Python :: 3.11
Classifier: Programming Language :: Python :: 3.12
Classifier: Topic :: Software Development :: Libraries
Classifier: Topic :: Utilities
Requires-Python: >=3.8
Requires-Dist: numpy>=1.26
Requires-Dist: openai>=1.0
Requires-Dist: python-dotenv>=1.0
Requires-Dist: scipy>=1.10
Requires-Dist: selenium>=4.10
Requires-Dist: sounddevice>=0.4
